{
  "project_info": {
    "project_number": "12920504952",
    "project_id": "agri-connect-36d65",
    "storage_bucket": "agri-connect-36d65.firebasestorage.app"
  },
  "client": [
    {
      "client_info": {
        "mobilesdk_app_id": "1:12920504952:android:4ada2e24fa8144946ba38d",
        "android_client_info": {
          "package_name": "com.example.agri_connect"
        }
      },
      "oauth_client": [],
      "api_key": [
        {
          "current_key": "AIzaSyCQxqmubKBevyoFMm9drJ1BC6Dl-lntgjk"
        }
      ],
      "services": {
        "appinvite_service": {
          "other_platform_oauth_client": []
        }
      }
    }
  ],
  "configuration_version": "1"
}